GMMchi_scs_pipeline/GMM_scs.py
GMMchi_scs_pipeline/__init__.py
GMMchi_scs_pipeline-0.1.dist-info/LICENSE
GMMchi_scs_pipeline-0.1.dist-info/METADATA
GMMchi_scs_pipeline-0.1.dist-info/WHEEL
GMMchi_scs_pipeline-0.1.dist-info/top_level.txt
GMMchi_scs_pipeline-0.1.dist-info/RECORD
