Metadata-Version: 2.1
Name: GMMchi-scs-pipeline
Version: 0.1
Summary: Pre-print version of the GMMchi-based single cell postprocessing pipeline
Home-page: https://github.com/jeffliu6068/GMMchi_scs_pipeline
Author: Jeff Liu
Author-email: jeffliu6068@gmail.com
License: LICENSE.txt
Platform: UNKNOWN
Requires-Dist: pandas
Requires-Dist: scipy
Requires-Dist: numpy
Requires-Dist: matplotlib
Requires-Dist: seaborn
Requires-Dist: sklearn
Requires-Dist: tqdm
Requires-Dist: umap-learn
Requires-Dist: scprep
